MANIFEST.in
README.rst
setup.py
psdl/__init__.py
psdl/clipboard.c
psdl/cpuinfo.c
psdl/events.c
psdl/sdl.c
psdl/version.c
psdl/video.c
psdl.egg-info/PKG-INFO
psdl.egg-info/SOURCES.txt
psdl.egg-info/dependency_links.txt
psdl.egg-info/not-zip-safe
psdl.egg-info/top_level.txt
psdl/gfxdraw/__init__.py
psdl/image/__init__.py
psdl/mixer/__init__.py
psdl/ttf/__init__.py
tests/__init__.py