Metadata-Version: 2.1
Name: psdl
Version: 0.0.1a1
Summary: A pythonic wrapper for SDL2
Home-page: https://github.com/ankith26/psdl
Author: Ankith (ankith26)
Author-email: itsankith26@gmail.com
License: UNKNOWN
Platform: UNKNOWN
Classifier: Development Status :: 2 - Pre-Alpha
Classifier: Intended Audience :: Developers
Classifier: Programming Language :: Python :: 3
Classifier: Programming Language :: Python :: 3.5
Classifier: Programming Language :: Python :: 3.6
Classifier: Programming Language :: Python :: 3.7
Classifier: Programming Language :: Python :: 3.8
Classifier: Programming Language :: Python :: 3.9
Classifier: License :: OSI Approved :: MIT License
Requires-Python: >=3.5
